{
  "character": "Sturdy Ass",
  "rules_applied": [
    "Q1: ge/gij dominant strict (eliminated je-family slips, verb conjugations adjusted: bent→zijt, mag→moogt, etc.)",
    "Q2: niet only — eliminated nie",
    "Q3: ik only — eliminated 'k. Sentence-start cap rule applied (Ik then lowercase next word).",
    "Q4: da-conj → dat (consistency doctrine, non-Thirsty)",
    "u/uw paradigm partners with ge/gij kept",
    "jullie kept",
    "kameraad×30 KEPT (signature address)",
    "'t×33 KEPT (heaviest 't user, signature contraction)",
    "'n×3 KEPT"
  ],
  "generated": "2026-04-28",
  "decision_status": "All Q1-Q4 locked. 46 cells.",
  "corrections": [
    {
      "id": "ST-Q1-1",
      "rationale": "Q1: je→ge",
      "file": "1_asses.masses_E1Proxy.xlsx",
      "sheet": "E1_Stable1F_localization",
      "cell": "J18",
      "speaker": "Sturdy Ass",
      "english": "But you're right.",
      "current_nl": "Maar je hebt gelijk.",
      "proposed_nl": "Maar ge hebt gelijk."
    },
    {
      "id": "ST-Q1-2",
      "rationale": "Q1: Je→Ge sentence-start",
      "file": "1_asses.masses_E1Proxy.xlsx",
      "sheet": "E1_Stable1F_localization",
      "cell": "J28",
      "speaker": "Sturdy Ass",
      "english": "Goodnight Trusty! You really care about the Herd and it shows.",
      "current_nl": "Goeie nacht, Trouwe. Je zit met onze Kudde in en dat zien we.",
      "proposed_nl": "Goeie nacht, Trouwe. Ge zit met onze Kudde in en dat zien we."
    },
    {
      "id": "ST-Q1-3",
      "rationale": "Q1: je→ge ×2 (subject + verb-inversion)",
      "file": "1_asses.masses_E1Proxy.xlsx",
      "sheet": "E1_Stable2F_localization",
      "cell": "J7",
      "speaker": "Sturdy Ass",
      "english": "Before you sleep, could you help me with something?",
      "current_nl": "Voor dat je gaat slapen, kan je me met iets helpen?",
      "proposed_nl": "Voor dat ge gaat slapen, kan ge me met iets helpen?"
    },
    {
      "id": "ST-Q1-4",
      "rationale": "Q1: Jij→Gij (emphatic subject)",
      "file": "1_asses.masses_E1Proxy.xlsx",
      "sheet": "E1_Stable2F_localization",
      "cell": "J48",
      "speaker": "Sturdy Ass",
      "english": "I'll stay with him. You lead the Herd, Comrade.",
      "current_nl": "Ik blijf bij hem. Jij moet de Kudde leiden, Kameraad.",
      "proposed_nl": "Ik blijf bij hem. Gij moet de Kudde leiden, Kameraad."
    },
    {
      "id": "ST-Q1-5",
      "rationale": "Q1: je→ge + verb mag→moogt (Flemish form)",
      "file": "1_asses.masses_E1Proxy.xlsx",
      "sheet": "E1_Stable2F_localization",
      "cell": "J57",
      "speaker": "Sturdy Ass",
      "english": "May you pass on in power to the Astral Plane, my dear Comrade.",
      "current_nl": "Dat je mag met kracht en liefde oversteken naar het Astrale Hiernamaals, Kameraad.",
      "proposed_nl": "Dat ge moogt met kracht en liefde oversteken naar het Astrale Hiernamaals, Kameraad."
    },
    {
      "id": "ST-Q1-6",
      "rationale": "Q1: je→u (object position, ge/u paradigm)",
      "file": "4_asses.masses_E4Proxy.xlsx",
      "sheet": "E4_Mine1F_localization",
      "cell": "J22",
      "speaker": "Sturdy Ass",
      "english": "Fear not Comrade, I'm confident that the Gods are watching over you.",
      "current_nl": "Heb geen vrees, Kameraad, Ik vertrouw dat de Goden over je zullen waken.",
      "proposed_nl": "Heb geen vrees, Kameraad, Ik vertrouw dat de Goden over u zullen waken."
    },
    {
      "id": "ST-Q1-7",
      "rationale": "Q1: je→ge (verb 'kon' kept for casual Flemish)",
      "file": "9_asses.masses_E9Proxy.xlsx",
      "sheet": "E9_MineEscape_localization",
      "cell": "J28",
      "speaker": "Sturdy Ass",
      "english": "How could you give up on our kind?",
      "current_nl": "Hoe kon je zo onze soort opgeven?",
      "proposed_nl": "Hoe kon ge zo onze soort opgeven?"
    },
    {
      "id": "ST-Q2-1",
      "rationale": "Q2: nie→niet",
      "file": "3_asses.masses_E3Proxy.xlsx",
      "sheet": "E3_Mine1F_localization",
      "cell": "J140",
      "speaker": "Sturdy Ass",
      "english": "Comrade, it's not safe outside.",
      "current_nl": "Kameraad, ’t is nie veilig buiten.",
      "proposed_nl": "Kameraad, ’t is niet veilig buiten."
    },
    {
      "id": "ST-Q2-2",
      "rationale": "Q2: nie→niet",
      "file": "3_asses.masses_E3Proxy.xlsx",
      "sheet": "E3_Mine1F_localization",
      "cell": "J141",
      "speaker": "Sturdy Ass",
      "english": "We can't go losing our Ace Strategist in a flood or a mudslide.",
      "current_nl": "We kunnen onze Topstrateeg nie kwijtspelen in een overstroming of een modderstroom.",
      "proposed_nl": "We kunnen onze Topstrateeg niet kwijtspelen in een overstroming of een modderstroom."
    },
    {
      "id": "ST-Q2-3",
      "rationale": "Q2: nie→niet",
      "file": "3_asses.masses_E3Proxy.xlsx",
      "sheet": "E3_Mine1F_localization",
      "cell": "J143",
      "speaker": "Sturdy Ass",
      "english": "The Gods won't leave us behind.",
      "current_nl": "De Goden laten ons nie achter.",
      "proposed_nl": "De Goden laten ons niet achter."
    },
    {
      "id": "ST-Q2-4",
      "rationale": "Q2: nie→niet",
      "file": "6_asses.masses_E6Proxy.xlsx",
      "sheet": "E6_World_localization",
      "cell": "J14",
      "speaker": "Sturdy Ass",
      "english": "Uncle Hard can't abandon his post.",
      "current_nl": "Oom Bikkehard kan zijn post nie verlaten, Kameraad.",
      "proposed_nl": "Oom Bikkehard kan zijn post niet verlaten, Kameraad."
    },
    {
      "id": "ST-Q2-5",
      "rationale": "Q2: nie→niet",
      "file": "6_asses.masses_E6Proxy.xlsx",
      "sheet": "E6_World_localization",
      "cell": "J24",
      "speaker": "Sturdy Ass",
      "english": "And if they ever come back, this isn't their home anymore.",
      "current_nl": "En als ze ooit terugkomen, dan is dit nie meer hun thuis, kameraad.",
      "proposed_nl": "En als ze ooit terugkomen, dan is dit niet meer hun thuis, kameraad."
    },
    {
      "id": "ST-Q2-6",
      "rationale": "Q2: nie→niet",
      "file": "6_asses.masses_E6Proxy.xlsx",
      "sheet": "E6_World_localization",
      "cell": "J62",
      "speaker": "Sturdy Ass",
      "english": "It's not safe. The Theatre might collapse at any moment.",
      "current_nl": "'t Is nie veilig. Het Theater kan elk moment instorten.",
      "proposed_nl": "'t Is niet veilig. Het Theater kan elk moment instorten."
    },
    {
      "id": "ST-Q2-7",
      "rationale": "Q2: nie→niet",
      "file": "6_asses.masses_E6Proxy.xlsx",
      "sheet": "E6_World_localization",
      "cell": "J63",
      "speaker": "Sturdy Ass",
      "english": "The structure lacks integrity and we can't fit through the door.",
      "current_nl": "De structuur mist elke integriteit en we passen nie door die deur, Kameraad.",
      "proposed_nl": "De structuur mist elke integriteit en we passen niet door die deur, Kameraad."
    },
    {
      "id": "ST-Q2-8",
      "rationale": "Q2: nie→niet",
      "file": "6_asses.masses_E6Proxy.xlsx",
      "sheet": "E6_World_localization",
      "cell": "J71",
      "speaker": "Sturdy Ass",
      "english": "No. It's not safe.",
      "current_nl": "Nee. 't Is nie veilig.",
      "proposed_nl": "Nee. 't Is niet veilig."
    },
    {
      "id": "ST-Q2-9",
      "rationale": "Q2: nie→niet",
      "file": "6_asses.masses_E6Proxy.xlsx",
      "sheet": "E6_World_localization",
      "cell": "J94",
      "speaker": "Sturdy Ass",
      "english": "And now it's just a pile of junk left behind and forgotten.",
      "current_nl": "En nu is 't nie meer dan een hoop rommel, achtergelaten en vergeten.",
      "proposed_nl": "En nu is 't niet meer dan een hoop rommel, achtergelaten en vergeten."
    },
    {
      "id": "ST-Q2-10",
      "rationale": "Q2: nie→niet",
      "file": "6_asses.masses_E6Proxy.xlsx",
      "sheet": "E6_World_localization",
      "cell": "J97",
      "speaker": "Sturdy Ass",
      "english": "And now it's just a pile of junk left behind and forgotten.",
      "current_nl": "En nu is 't nie meer dan een hoop rommel, achtergelaten en vergeten.",
      "proposed_nl": "En nu is 't niet meer dan een hoop rommel, achtergelaten en vergeten."
    },
    {
      "id": "ST-Q2-11",
      "rationale": "Q2: nie→niet",
      "file": "6_asses.masses_E6Proxy.xlsx",
      "sheet": "E6_World_localization",
      "cell": "J103",
      "speaker": "Sturdy Ass",
      "english": "And now it's just a pile of junk left behind and forgotten.",
      "current_nl": "En nu is 't nie meer dan een hoop rommel, achtergelaten en vergeten.",
      "proposed_nl": "En nu is 't niet meer dan een hoop rommel, achtergelaten en vergeten."
    },
    {
      "id": "ST-Q2-12",
      "rationale": "Q2: nie→niet",
      "file": "6_asses.masses_E6Proxy.xlsx",
      "sheet": "E6_World_localization",
      "cell": "J106",
      "speaker": "Sturdy Ass",
      "english": "And now it's just a pile of junk left behind and forgotten.",
      "current_nl": "En nu is 't nie meer dan een hoop rommel, achtergelaten en vergeten.",
      "proposed_nl": "En nu is 't niet meer dan een hoop rommel, achtergelaten en vergeten."
    },
    {
      "id": "ST-Q2-13",
      "rationale": "Q2: nie→niet",
      "file": "6_asses.masses_E6Proxy.xlsx",
      "sheet": "E6_World_localization",
      "cell": "J218",
      "speaker": "Sturdy Ass",
      "english": "This pile isn't very inspiring...",
      "current_nl": "Deze hoop is nie echt inspirerend...",
      "proposed_nl": "Deze hoop is niet echt inspirerend..."
    },
    {
      "id": "ST-Q2-14",
      "rationale": "Q2: nie→niet",
      "file": "9_asses.masses_E9Proxy.xlsx",
      "sheet": "E9_GoldenAss_localization",
      "cell": "J52",
      "speaker": "Sturdy Ass",
      "english": "You can't let a Machine become a Prophet!",
      "current_nl": "Ge kunt toch nie een Machine Profeet laten worden!",
      "proposed_nl": "Ge kunt toch niet een Machine Profeet laten worden!"
    },
    {
      "id": "ST-Q2-15",
      "rationale": "Q2: nie→niet",
      "file": "9_asses.masses_E9Proxy.xlsx",
      "sheet": "E9_MineEscape_localization",
      "cell": "J4",
      "speaker": "Sturdy Ass",
      "english": "Don't touch me!",
      "current_nl": "Raak me nie aan!",
      "proposed_nl": "Raak me niet aan!"
    },
    {
      "id": "ST-Q3-1",
      "rationale": "Q3: 'k→ik (with cap rule)",
      "file": "6_asses.masses_E6Proxy.xlsx",
      "sheet": "E6_World_localization",
      "cell": "J153",
      "speaker": "Sturdy Ass",
      "english": "Being an artist is one of the most spiritual things I've done with my life.",
      "current_nl": "Kunstenaar zijn is een van de meest spirituele dingen die 'k ooit met mijn leven gedaan heb.",
      "proposed_nl": "Kunstenaar zijn is een van de meest spirituele dingen die ik ooit met mijn leven gedaan heb."
    },
    {
      "id": "ST-Q3-2",
      "rationale": "Q3: 'k→ik (with cap rule)",
      "file": "9_asses.masses_E9Proxy.xlsx",
      "sheet": "E9_BadCave_localization",
      "cell": "J40",
      "speaker": "Sturdy Ass",
      "english": "I thought you were playing ROCKS with your UNCLE!",
      "current_nl": "'k dacht dat ge STENEN-SPEL aan 't spelen waart met uw NONKEL!\"",
      "proposed_nl": "Ik dacht dat ge STENEN-SPEL aan 't spelen waart met uw NONKEL!\""
    },
    {
      "id": "ST-Q3-3",
      "rationale": "Q3: 'k→ik (with cap rule)",
      "file": "9_asses.masses_E9Proxy.xlsx",
      "sheet": "E9_MineEscape_localization",
      "cell": "J23",
      "speaker": "Sturdy Ass",
      "english": "Daughter? I've lost both my daughters now...",
      "current_nl": "Dochter? 'k Heb nu al m'n twee dochters verloren...",
      "proposed_nl": "Dochter? Ik heb nu al m'n twee dochters verloren..."
    },
    {
      "id": "ST-Q3-4",
      "rationale": "Q3: 'k→ik (with cap rule)",
      "file": "9_asses.masses_E9Proxy.xlsx",
      "sheet": "E9_MineEscape_localization",
      "cell": "J24",
      "speaker": "Sturdy Ass",
      "english": "I have nothing left.",
      "current_nl": "'k Heb niks meer over.",
      "proposed_nl": "Ik heb niks meer over."
    },
    {
      "id": "ST-Q4-1",
      "rationale": "Q4: da→dat",
      "file": "10_asses.masses_E10Proxy.xlsx",
      "sheet": "E10_Epilogue_localization",
      "cell": "J3",
      "speaker": "Sturdy Ass",
      "english": "And that is why every Ass today is born with the Soul of a Revolutionary—",
      "current_nl": "En da is waarom elke Ezel vandaag geboren wordt met de Ziel van een Revolutionair—",
      "proposed_nl": "En dat is waarom elke Ezel vandaag geboren wordt met de Ziel van een Revolutionair—"
    },
    {
      "id": "ST-Q4-2",
      "rationale": "Q4: da→dat",
      "file": "10_asses.masses_E10Proxy.xlsx",
      "sheet": "E10_Epilogue_localization",
      "cell": "J16",
      "speaker": "Sturdy Ass",
      "english": "We can't leave this work to the Gods.",
      "current_nl": "We kunnen da werk niet aan de Goden overlaten.",
      "proposed_nl": "We kunnen dat werk niet aan de Goden overlaten."
    },
    {
      "id": "ST-Q4-3",
      "rationale": "Q4: da→dat",
      "file": "10_asses.masses_E10Proxy.xlsx",
      "sheet": "E10_Epilogue_localization",
      "cell": "J26",
      "speaker": "Sturdy Ass",
      "english": "To live a life that is just.",
      "current_nl": "Om een leven te leiden da rechtvaardig is.",
      "proposed_nl": "Om een leven te leiden dat rechtvaardig is."
    },
    {
      "id": "ST-Q4-4",
      "rationale": "Q4: da→dat",
      "file": "10_asses.masses_E10Proxy.xlsx",
      "sheet": "E10_Epilogue_localization",
      "cell": "J28",
      "speaker": "Sturdy Ass",
      "english": "But when it comes, I hope you will be part of it.",
      "current_nl": "Maar als 't zover is, hoop ik da ge er deel van zult uitmaken.",
      "proposed_nl": "Maar als 't zover is, hoop ik dat ge er deel van zult uitmaken."
    },
    {
      "id": "ST-Q4-5",
      "rationale": "Q4: da→dat",
      "file": "10_asses.masses_E10Proxy.xlsx",
      "sheet": "E10_Epilogue_localization",
      "cell": "J29",
      "speaker": "Sturdy Ass",
      "english": "We can't leave this work to the Gods.",
      "current_nl": "We kunnen da werk niet aan de Goden overlaten.",
      "proposed_nl": "We kunnen dat werk niet aan de Goden overlaten."
    },
    {
      "id": "ST-Q4-6",
      "rationale": "Q4: da→dat",
      "file": "3_asses.masses_E3Proxy.xlsx",
      "sheet": "E3_Mine1F_localization",
      "cell": "J3",
      "speaker": "Sturdy Ass",
      "english": "HEY! Where do you think you are going?",
      "current_nl": "HEY! Waar denkt ge da ge naartoe gaat?!",
      "proposed_nl": "HEY! Waar denkt ge dat ge naartoe gaat?!"
    },
    {
      "id": "ST-Q4-7",
      "rationale": "Q4: da→dat",
      "file": "6_asses.masses_E6Proxy.xlsx",
      "sheet": "E6_World_localization",
      "cell": "J38",
      "speaker": "Sturdy Ass",
      "english": "I'll have to bring {$NewName} here next time we have quality time together.",
      "current_nl": "Ik zal {$NewName} hier eens mee naartoe moeten nemen, de volgende keer da we samen wat tijd voor ons hebben.",
      "proposed_nl": "Ik zal {$NewName} hier eens mee naartoe moeten nemen, de volgende keer dat we samen wat tijd voor ons hebben."
    },
    {
      "id": "ST-Q4-8",
      "rationale": "Q4: da→dat",
      "file": "6_asses.masses_E6Proxy.xlsx",
      "sheet": "E6_World_localization",
      "cell": "J40",
      "speaker": "Sturdy Ass",
      "english": "It's a shame you never saw this place as it was, before the Fire, before the Machines.",
      "current_nl": "'t Is jammer da ge deze plek nooit gezien hebt zoals ze was, vóór het Vuur, vóór de Machines.",
      "proposed_nl": "'t Is jammer dat ge deze plek nooit gezien hebt zoals ze was, vóór het Vuur, vóór de Machines."
    },
    {
      "id": "ST-Q4-9",
      "rationale": "Q4: da→dat",
      "file": "6_asses.masses_E6Proxy.xlsx",
      "sheet": "E6_World_localization",
      "cell": "J46",
      "speaker": "Sturdy Ass",
      "english": "It's a shame you never saw this place as it was, before the Fire, before the Machines.",
      "current_nl": "'t Is zonde da ge deze plek nooit gezien hebt zoals ze was, vóór het Vuur, vóór de Machines.",
      "proposed_nl": "'t Is zonde dat ge deze plek nooit gezien hebt zoals ze was, vóór het Vuur, vóór de Machines."
    },
    {
      "id": "ST-Q4-10",
      "rationale": "Q4: da→dat",
      "file": "6_asses.masses_E6Proxy.xlsx",
      "sheet": "E6_World_localization",
      "cell": "J68",
      "speaker": "Sturdy Ass",
      "english": "Fine... I suppose you're getting old enough to make your own decisions—",
      "current_nl": "Vooruit dan maar... Ik veronderstel da ge oud genoeg zijt om uw eigen beslissingen te nemen—",
      "proposed_nl": "Vooruit dan maar... Ik veronderstel dat ge oud genoeg zijt om uw eigen beslissingen te nemen—"
    },
    {
      "id": "ST-Q4-11",
      "rationale": "Q4: da→dat",
      "file": "6_asses.masses_E6Proxy.xlsx",
      "sheet": "E6_World_localization",
      "cell": "J100",
      "speaker": "Sturdy Ass",
      "english": "And now it's just a pile of junk left behind and forgotten.",
      "current_nl": "En nu is 't gewoon een hoop rommel da achtergelaten en vergeten is.",
      "proposed_nl": "En nu is 't gewoon een hoop rommel dat achtergelaten en vergeten is."
    },
    {
      "id": "ST-Q4-12",
      "rationale": "Q4: da→dat",
      "file": "6_asses.masses_E6Proxy.xlsx",
      "sheet": "E6_World_localization",
      "cell": "J112",
      "speaker": "Sturdy Ass",
      "english": "And now it's just a pile of junk left behind and forgotten.",
      "current_nl": "En nu is 't gewoon een hoop rommel da achtergelaten en vergeten is.",
      "proposed_nl": "En nu is 't gewoon een hoop rommel dat achtergelaten en vergeten is."
    },
    {
      "id": "ST-Q4-13",
      "rationale": "Q4: da→dat",
      "file": "6_asses.masses_E6Proxy.xlsx",
      "sheet": "E6_World_localization",
      "cell": "J169",
      "speaker": "Sturdy Ass",
      "english": "Those months we spent in the Mine were a constant reminder of how I lost my beloved daughter, Lazy.",
      "current_nl": "Die maanden da we in de Mijn doorbrachten waren een constante herinnering aan hoe ik mijn geliefde dochter verloren heb, Luie.",
      "proposed_nl": "Die maanden dat we in de Mijn doorbrachten waren een constante herinnering aan hoe ik mijn geliefde dochter verloren heb, Luie."
    },
    {
      "id": "ST-Q4-14",
      "rationale": "Q4: da→dat",
      "file": "6_asses.masses_E6Proxy.xlsx",
      "sheet": "E6_World_localization",
      "cell": "J187",
      "speaker": "Sturdy Ass",
      "english": "I'm glad you found what you're good at Comrade.",
      "current_nl": "Ik ben blij da ge gevonden hebt waar ge goed in zijt, Kameraad.",
      "proposed_nl": "Ik ben blij dat ge gevonden hebt waar ge goed in zijt, Kameraad."
    },
    {
      "id": "ST-Q4-15",
      "rationale": "Q4: da→dat",
      "file": "6_asses.masses_E6Proxy.xlsx",
      "sheet": "E6_World_localization",
      "cell": "J229",
      "speaker": "Sturdy Ass",
      "english": "I think Thirsty will jump for joy when he sees this!",
      "current_nl": "Ik denk da Beschonken Ezel een gat in de lucht springt als hij dit ziet!",
      "proposed_nl": "Ik denk dat Beschonken Ezel een gat in de lucht springt als hij dit ziet!"
    },
    {
      "id": "ST-Q4-16",
      "rationale": "Q4: da→dat",
      "file": "6_asses.masses_E6Proxy.xlsx",
      "sheet": "E6_World_localization",
      "cell": "J304",
      "speaker": "Sturdy Ass",
      "english": "Comrades, I think we need to remember that—",
      "current_nl": "Kameraden, ik denk da ge moet onthouden dat—",
      "proposed_nl": "Kameraden, ik denk dat ge moet onthouden dat—"
    },
    {
      "id": "ST-Q4-17",
      "rationale": "Q4: da→dat",
      "file": "6_asses.masses_E6Proxy.xlsx",
      "sheet": "E6_World_localization",
      "cell": "J344",
      "speaker": "Sturdy Ass",
      "english": "Go without me—I'm sure the Gods have already given up on you.",
      "current_nl": "Ga maar zonder mij—ik ben er zeker van da de Goden u allang hebben opgegeven.",
      "proposed_nl": "Ga maar zonder mij—ik ben er zeker van dat de Goden u allang hebben opgegeven."
    },
    {
      "id": "ST-Q4-18",
      "rationale": "Q4: da→dat",
      "file": "9_asses.masses_E9Proxy.xlsx",
      "sheet": "E9_BadCave_localization",
      "cell": "J48",
      "speaker": "Sturdy Ass",
      "english": "And why do you keep calling that thing Cole?!",
      "current_nl": "\"En waarom blijft ge da ding Piet noemen?!\"",
      "proposed_nl": "\"En waarom blijft ge dat ding Piet noemen?!\""
    },
    {
      "id": "ST-Q34-1",
      "rationale": "Q3: 'k→ik (with cap rule)",
      "file": "6_asses.masses_E6Proxy.xlsx",
      "sheet": "E6_World_localization",
      "cell": "J133",
      "speaker": "Sturdy Ass",
      "english": "Does being a mother define me?",
      "current_nl": "Bepaalt moeder-zijn wie da'k ben?",
      "proposed_nl": "Bepaalt moeder-zijn wie dat ik ben?"
    },
    {
      "id": "ST-Q24-1",
      "rationale": "Q2: nie→niet",
      "file": "6_asses.masses_E6Proxy.xlsx",
      "sheet": "E6_World_localization",
      "cell": "J326",
      "speaker": "Sturdy Ass",
      "english": "Isn't that right, Comrade Hard?",
      "current_nl": "Ist da nie waar, Kameraad Bikkelharde?",
      "proposed_nl": "Ist dat niet waar, Kameraad Bikkelharde?"
    }
  ]
}